jsac/torch_train_loop/__init__.py
jsac/torch_train_loop/_static_version.py
jsac/torch_train_loop/_version.py
jsac/torch_train_loop/core.py
jsac/torch_train_loop/helpers.py
jsac/torch_train_loop/input_parsers.py
torch_train_loop-0.0.2.dist-info/LICENSE.txt
torch_train_loop-0.0.2.dist-info/METADATA
torch_train_loop-0.0.2.dist-info/WHEEL
torch_train_loop-0.0.2.dist-info/top_level.txt
torch_train_loop-0.0.2.dist-info/RECORD
