Metadata-Version: 2.1
Name: torch-train-loop
Version: 0.0.2
Summary: General-purpose train-loop for PyTorch models
Author-email: Jorge Sacristan <j.sacris@gmail.com>
License: MIT License
Project-URL: GitHub, https://github.com/jsacrist/jsac-torch-train-loop/
Project-URL: Bug Tracker, https://github.com/jsacrist/jsac-torch-train-loop/issues
Classifier: Programming Language :: Python :: 3 :: Only
Classifier: Programming Language :: Python :: 3.10
Classifier: Operating System :: OS Independent
Requires-Python: >=3.10
License-File: LICENSE.txt
Requires-Dist: torch
Requires-Dist: tqdm
Requires-Dist: tensorboard
